{
  "title": "株洲市地面数字电视节目表查询—中文寻星",
  "update": "2024-03-13 19:23:14",
  "url": "http://dtmb.saoing.com/zhuzhou.htm",
  "count": 184,
  "info": [
    {
      "频率": "514",
      "极化": "",
      "SID": "",
      "color_channel": "#808000",
      "频道名称": "中央电视台农业农村频道",
      "link_channel": "",
      "视频编码": "AVS+",
      "音频编码": "DRA",
      "锁码方式": "开锁",
      "V-PID": "",
      "A-PID": "",
      "发射基站": "醴陵市电视转播台",
      "高阶参数": "",
      "来源": "柠檬我不萌2019-12-23",
      "color_source": "#666666",
      "link_source": ""
    },
    {
      "频率": "514",
      "极化": "",
      "SID": "",
      "color_channel": "#808000",
      "频道名称": "中央电视台纪录频道",
      "link_channel": "",
      "视频编码": "AVS+",
      "音频编码": "DRA",
      "锁码方式": "开锁",
      "V-PID": "",
      "A-PID": "",
      "发射基站": "醴陵市电视转播台",
      "高阶参数": "",
      "来源": "柠檬我不萌2019-12-23",
      "color_source": "#666666",
      "link_source": ""
    },
    {
      "频率": "514",
      "极化": "",
      "SID": "",
      "color_channel": "#808000",
      "频道名称": "中央电视台戏曲频道",
      "link_channel": "",
      "视频编码": "AVS+",
      "音频编码": "DRA",
      "锁码方式": "开锁",
      "V-PID": "",
      "A-PID": "",
      "发射基站": "醴陵市电视转播台",
      "高阶参数": "",
      "来源": "柠檬我不萌2019-12-23",
      "color_source": "#666666",
      "link_source": ""
    },
    {
      "频率": "514",
      "极化": "",
      "SID": "",
      "color_channel": "#808000",
      "频道名称": "中国环球电视网新闻频道",
      "link_channel": "",
      "视频编码": "AVS+",
      "音频编码": "DRA",
      "锁码方式": "开锁",
      "V-PID": "",
      "A-PID": "",
      "发射基站": "醴陵市电视转播台",
      "高阶参数": "",
      "来源": "柠檬我不萌2019-12-23",
      "color_source": "#666666",
      "link_source": ""
    },
    {
      "频率": "514",
      "极化": "",
      "SID": "",
      "color_channel": "#808000",
      "频道名称": "湖南卫视",
      "link_channel": "",
      "视频编码": "AVS+",
      "音频编码": "DRA",
      "锁码方式": "开锁",
      "V-PID": "",
      "A-PID": "",
      "发射基站": "醴陵市电视转播台",
      "高阶参数": "",
      "来源": "柠檬我不萌2019-12-23",
      "color_source": "#666666",
      "link_source": ""
    },
    {
      "频率": "514",
      "极化": "",
      "SID": "",
      "color_channel": "#808000",
      "频道名称": "湖南经视",
      "link_channel": "",
      "视频编码": "AVS+",
      "音频编码": "DRA",
      "锁码方式": "开锁",
      "V-PID": "",
      "A-PID": "",
      "发射基站": "醴陵市电视转播台",
      "高阶参数": "",
      "来源": "柠檬我不萌2019-12-23",
      "color_source": "#666666",
      "link_source": ""
    },
    {
      "频率": "514",
      "极化": "",
      "SID": "",
      "color_channel": "#808000",
      "频道名称": "湖南都市",
      "link_channel": "",
      "视频编码": "AVS+",
      "音频编码": "DRA",
      "锁码方式": "开锁",
      "V-PID": "",
      "A-PID": "",
      "发射基站": "醴陵市电视转播台",
      "高阶参数": "",
      "来源": "柠檬我不萌2019-12-23",
      "color_source": "#666666",
      "link_source": ""
    },
    {
      "频率": "514",
      "极化": "",
      "SID": "",
      "color_channel": "#808000",
      "频道名称": "湖南电视剧",
      "link_channel": "",
      "视频编码": "AVS+",
      "音频编码": "DRA",
      "锁码方式": "开锁",
      "V-PID": "",
      "A-PID": "",
      "发射基站": "醴陵市电视转播台",
      "高阶参数": "",
      "来源": "柠檬我不萌2019-12-23",
      "color_source": "#666666",
      "link_source": ""
    },
    {
      "频率": "514",
      "极化": "",
      "SID": "",
      "color_channel": "#808000",
      "频道名称": "湖南娱乐",
      "link_channel": "",
      "视频编码": "AVS+",
      "音频编码": "DRA",
      "锁码方式": "开锁",
      "V-PID": "",
      "A-PID": "",
      "发射基站": "醴陵市电视转播台",
      "高阶参数": "",
      "来源": "柠檬我不萌2019-12-23",
      "color_source": "#666666",
      "link_source": ""
    },
    {
      "频率": "514",
      "极化": "",
      "SID": "",
      "color_channel": "#808000",
      "频道名称": "株洲新闻综合",
      "link_channel": "",
      "视频编码": "AVS+",
      "音频编码": "DRA",
      "锁码方式": "开锁",
      "V-PID": "",
      "A-PID": "",
      "发射基站": "醴陵市电视转播台",
      "高阶参数": "",
      "来源": "柠檬我不萌2019-12-23",
      "color_source": "#666666",
      "link_source": ""
    },
    {
      "频率": "514",
      "极化": "",
      "SID": "",
      "color_channel": "#808000",
      "频道名称": "酸陵新闻",
      "link_channel": "",
      "视频编码": "AVS+",
      "音频编码": "DRA",
      "锁码方式": "开锁",
      "V-PID": "",
      "A-PID": "",
      "发射基站": "醴陵市电视转播台",
      "高阶参数": "",
      "来源": "柠檬我不萌2019-12-23",
      "color_source": "#666666",
      "link_source": ""
    },
    {
      "频率": "522",
      "极化": "",
      "SID": "110",
      "color_channel": "#808000",
      "频道名称": "金鹰经视",
      "link_channel": "",
      "视频编码": "AVS+",
      "音频编码": "DRA",
      "锁码方式": "开锁",
      "V-PID": "111",
      "A-PID": "112",
      "发射基站": "炎陵 茶陵云阳山",
      "高阶参数": "16QAM PN945 4/5(0.8)",
      "来源": "q1060896983 2024-02-08",
      "color_source": "#FF9933",
      "link_source": ""
    },
    {
      "频率": "522",
      "极化": "",
      "SID": "",
      "color_channel": "#808000",
      "频道名称": "金鹰都市",
      "link_channel": "",
      "视频编码": "AVS+",
      "音频编码": "DRA",
      "锁码方式": "开锁",
      "V-PID": "121",
      "A-PID": "122",
      "发射基站": "炎陵 茶陵云阳山",
      "高阶参数": "16QAM PN945 4/5(0.8)",
      "来源": "q1060896983 2024-02-08",
      "color_source": "#FF9933",
      "link_source": ""
    },
    {
      "频率": "522",
      "极化": "",
      "SID": "",
      "color_channel": "#808000",
      "频道名称": "湖南电视剧",
      "link_channel": "",
      "视频编码": "AVS+",
      "音频编码": "DRA",
      "锁码方式": "开锁",
      "V-PID": "141",
      "A-PID": "142",
      "发射基站": "炎陵 茶陵云阳山",
      "高阶参数": "16QAM PN945 4/5(0.8)",
      "来源": "q1060896983 2024-02-08",
      "color_source": "#FF9933",
      "link_source": ""
    },
    {
      "频率": "522",
      "极化": "",
      "SID": "150",
      "color_channel": "#808000",
      "频道名称": "金鹰纪实",
      "link_channel": "",
      "视频编码": "AVS+",
      "音频编码": "DRA",
      "锁码方式": "开锁",
      "V-PID": "151",
      "A-PID": "152",
      "发射基站": "炎陵 茶陵云阳山",
      "高阶参数": "16QAM PN945 4/5(0.8)",
      "来源": "q1060896983 2024-02-08",
      "color_source": "#FF9933",
      "link_source": ""
    },
    {
      "频率": "522",
      "极化": "",
      "SID": "",
      "color_channel": "#808000",
      "频道名称": "金鹰卡通",
      "link_channel": "",
      "视频编码": "AVS+",
      "音频编码": "DRA",
      "锁码方式": "开锁",
      "V-PID": "161",
      "A-PID": "162",
      "发射基站": "炎陵 茶陵云阳山",
      "高阶参数": "16QAM PN945 4/5(0.8)",
      "来源": "q1060896983 2024-02-08",
      "color_source": "#FF9933",
      "link_source": ""
    },
    {
      "频率": "522",
      "极化": "",
      "SID": "",
      "color_channel": "#808000",
      "频道名称": "中国国家应急广播",
      "link_channel": "",
      "视频编码": "MPEG-2",
      "音频编码": "MPEG-1",
      "锁码方式": "开锁",
      "V-PID": "888",
      "A-PID": "999",
      "发射基站": "炎陵 茶陵云阳山",
      "高阶参数": "16QAM PN945 4/5(0.8)",
      "来源": "q1060896983 2024-02-08",
      "color_source": "#FF9933",
      "link_source": ""
    },
    {
      "频率": "522",
      "极化": "",
      "SID": "",
      "color_channel": "#808000",
      "频道名称": "中央电视台综合频道",
      "link_channel": "",
      "视频编码": "AVS+",
      "音频编码": "DRA",
      "锁码方式": "开锁",
      "V-PID": "512",
      "A-PID": "650",
      "发射基站": "醴陵市电视转播台",
      "高阶参数": "",
      "来源": "柠檬我不萌i 2020-01-10",
      "color_source": "#666666",
      "link_source": ""
    },
    {
      "频率": "522",
      "极化": "",
      "SID": "",
      "color_channel": "#808000",
      "频道名称": "中央电视台财经频道",
      "link_channel": "",
      "视频编码": "AVS+",
      "音频编码": "DRA",
      "锁码方式": "开锁",
      "V-PID": "513",
      "A-PID": "660",
      "发射基站": "醴陵市电视转播台",
      "高阶参数": "",
      "来源": "柠檬我不萌i 2020-01-10",
      "color_source": "#666666",
      "link_source": ""
    },
    {
      "频率": "522",
      "极化": "",
      "SID": "",
      "color_channel": "#808000",
      "频道名称": "中央电视台中文国际频道",
      "link_channel": "",
      "视频编码": "AVS+",
      "音频编码": "DRA",
      "锁码方式": "开锁",
      "V-PID": "514",
      "A-PID": "670",
      "发射基站": "醴陵市电视转播台",
      "高阶参数": "",
      "来源": "柠檬我不萌i 2020-01-10",
      "color_source": "#666666",
      "link_source": ""
    },
    {
      "频率": "522",
      "极化": "",
      "SID": "",
      "color_channel": "#808000",
      "频道名称": "中央电视台科教频道",
      "link_channel": "http://www.cctv.com",
      "视频编码": "AVS+",
      "音频编码": "DRA",
      "锁码方式": "开锁",
      "V-PID": "515",
      "A-PID": "680",
      "发射基站": "醴陵市电视转播台",
      "高阶参数": "",
      "来源": "柠檬我不萌i 2020-01-10",
      "color_source": "#666666",
      "link_source": ""
    },
    {
      "频率": "522",
      "极化": "",
      "SID": "",
      "color_channel": "#808000",
      "频道名称": "中央电视台社会与法频道",
      "link_channel": "http://www.cctv.com",
      "视频编码": "AVS+",
      "音频编码": "DRA",
      "锁码方式": "开锁",
      "V-PID": "516",
      "A-PID": "690",
      "发射基站": "醴陵市电视转播台",
      "高阶参数": "",
      "来源": "柠檬我不萌i 2020-01-10",
      "color_source": "#666666",
      "link_source": ""
    },
    {
      "频率": "522",
      "极化": "",
      "SID": "",
      "color_channel": "#808000",
      "频道名称": "中央电视台新闻频道",
      "link_channel": "http://www.cctv.com",
      "视频编码": "AVS+",
      "音频编码": "DRA",
      "锁码方式": "开锁",
      "V-PID": "517",
      "A-PID": "700",
      "发射基站": "醴陵市电视转播台",
      "高阶参数": "",
      "来源": "柠檬我不萌i 2020-01-10",
      "color_source": "#666666",
      "link_source": ""
    },
    {
      "频率": "522",
      "极化": "",
      "SID": "",
      "color_channel": "#808000",
      "频道名称": "中央电视台少儿频道",
      "link_channel": "",
      "视频编码": "AVS+",
      "音频编码": "DRA",
      "锁码方式": "开锁",
      "V-PID": "518",
      "A-PID": "710",
      "发射基站": "醴陵市电视转播台",
      "高阶参数": "",
      "来源": "柠檬我不萌i 2020-01-10",
      "color_source": "#666666",
      "link_source": ""
    },
    {
      "频率": "522",
      "极化": "",
      "SID": "",
      "color_channel": "#808000",
      "频道名称": "中央电视台音乐频道",
      "link_channel": "",
      "视频编码": "AVS+",
      "音频编码": "DRA",
      "锁码方式": "开锁",
      "V-PID": "",
      "A-PID": "",
      "发射基站": "醴陵市电视转播台",
      "高阶参数": "",
      "来源": "柠檬我不萌i 2020-01-10",
      "color_source": "#666666",
      "link_source": ""
    },
    {
      "频率": "530",
      "极化": "",
      "SID": "50",
      "color_channel": "#808000",
      "频道名称": "中央电视台社会与法频道",
      "link_channel": "http://www.cctv.com",
      "视频编码": "AVS+",
      "音频编码": "DRA",
      "锁码方式": "开锁",
      "V-PID": "52",
      "A-PID": "53",
      "发射基站": "株洲神农塔 茶陵云阳山",
      "高阶参数": "",
      "来源": "天涯海角 2022-10-17",
      "color_source": "#FF9933",
      "link_source": ""
    },
    {
      "频率": "530",
      "极化": "",
      "SID": "60",
      "color_channel": "#808000",
      "频道名称": "中央电视台新闻频道",
      "link_channel": "http://www.cctv.com",
      "视频编码": "AVS+",
      "音频编码": "DRA",
      "锁码方式": "开锁",
      "V-PID": "61",
      "A-PID": "62",
      "发射基站": "株洲神农塔 茶陵云阳山",
      "高阶参数": "",
      "来源": "天涯海角 2022-10-17",
      "color_source": "#FF9933",
      "link_source": ""
    },
    {
      "频率": "530",
      "极化": "",
      "SID": "70",
      "color_channel": "#808000",
      "频道名称": "中央电视台少儿频道",
      "link_channel": "",
      "视频编码": "AVS+",
      "音频编码": "DRA",
      "锁码方式": "开锁",
      "V-PID": "71",
      "A-PID": "72",
      "发射基站": "株洲神农塔 茶陵云阳山",
      "高阶参数": "",
      "来源": "天涯海角 2022-10-17",
      "color_source": "#FF9933",
      "link_source": ""
    },
    {
      "频率": "530",
      "极化": "",
      "SID": "80",
      "color_channel": "#808000",
      "频道名称": "中央电视台音乐频道",
      "link_channel": "",
      "视频编码": "AVS+",
      "音频编码": "DRA",
      "锁码方式": "开锁",
      "V-PID": "81",
      "A-PID": "82",
      "发射基站": "株洲神农塔 茶陵云阳山",
      "高阶参数": "",
      "来源": "天涯海角 2022-10-17",
      "color_source": "#FF9933",
      "link_source": ""
    },
    {
      "频率": "530",
      "极化": "",
      "SID": "90",
      "color_channel": "#808000",
      "频道名称": "中央电视台综合频道",
      "link_channel": "",
      "视频编码": "AVS+",
      "音频编码": "DRA",
      "锁码方式": "开锁",
      "V-PID": "91",
      "A-PID": "92",
      "发射基站": "株洲神农塔 茶陵云阳山",
      "高阶参数": "",
      "来源": "天涯海角 2022-10-17",
      "color_source": "#FF9933",
      "link_source": ""
    },
    {
      "频率": "530",
      "极化": "",
      "SID": "100",
      "color_channel": "#808000",
      "频道名称": "中央电视台财经频道",
      "link_channel": "",
      "视频编码": "AVS+",
      "音频编码": "DRA",
      "锁码方式": "开锁",
      "V-PID": "101",
      "A-PID": "102",
      "发射基站": "株洲神农塔 茶陵云阳山",
      "高阶参数": "",
      "来源": "天涯海角 2022-10-17",
      "color_source": "#FF9933",
      "link_source": ""
    },
    {
      "频率": "530",
      "极化": "",
      "SID": "110",
      "color_channel": "#808000",
      "频道名称": "中央电视台中文国际频道",
      "link_channel": "",
      "视频编码": "AVS+",
      "音频编码": "DRA",
      "锁码方式": "开锁",
      "V-PID": "111",
      "A-PID": "111",
      "发射基站": "株洲神农塔 茶陵云阳山",
      "高阶参数": "",
      "来源": "天涯海角 2022-10-17",
      "color_source": "#FF9933",
      "link_source": ""
    },
    {
      "频率": "530",
      "极化": "",
      "SID": "120",
      "color_channel": "#808000",
      "频道名称": "中央电视台科教频道",
      "link_channel": "http://www.cctv.com",
      "视频编码": "AVS+",
      "音频编码": "DRA",
      "锁码方式": "开锁",
      "V-PID": "121",
      "A-PID": "122",
      "发射基站": "株洲神农塔 茶陵云阳山",
      "高阶参数": "",
      "来源": "天涯海角 2022-10-17",
      "color_source": "#FF9933",
      "link_source": ""
    },
    {
      "频率": "530",
      "极化": "",
      "SID": "",
      "color_channel": "#9933FF",
      "频道名称": "中国之声",
      "link_channel": "",
      "视频编码": "",
      "音频编码": "MPEG-1",
      "锁码方式": "开锁",
      "V-PID": "",
      "A-PID": "730",
      "发射基站": "株洲神农塔 茶陵云阳山",
      "高阶参数": "",
      "来源": "天涯海角 2022-10-17",
      "color_source": "#FF9933",
      "link_source": ""
    },
    {
      "频率": "530",
      "极化": "",
      "SID": "",
      "color_channel": "#9933FF",
      "频道名称": "经济之声",
      "link_channel": "",
      "视频编码": "",
      "音频编码": "MPEG-1",
      "锁码方式": "开锁",
      "V-PID": "",
      "A-PID": "740",
      "发射基站": "株洲神农塔 茶陵云阳山",
      "高阶参数": "",
      "来源": "天涯海角 2022-10-17",
      "color_source": "#FF9933",
      "link_source": ""
    },
    {
      "频率": "530",
      "极化": "",
      "SID": "",
      "color_channel": "#9933FF",
      "频道名称": "音乐之声",
      "link_channel": "",
      "视频编码": "",
      "音频编码": "MPEG-1",
      "锁码方式": "开锁",
      "V-PID": "",
      "A-PID": "750",
      "发射基站": "株洲神农塔 茶陵云阳山",
      "高阶参数": "",
      "来源": "天涯海角 2022-10-17",
      "color_source": "#FF9933",
      "link_source": ""
    },
    {
      "频率": "530",
      "极化": "",
      "SID": "",
      "color_channel": "#9933FF",
      "频道名称": "经典音乐广播",
      "link_channel": "",
      "视频编码": "",
      "音频编码": "MPEG-1",
      "锁码方式": "开锁",
      "V-PID": "",
      "A-PID": "760",
      "发射基站": "株洲神农塔 茶陵云阳山",
      "高阶参数": "",
      "来源": "天涯海角 2022-10-17",
      "color_source": "#FF9933",
      "link_source": ""
    },
    {
      "频率": "530",
      "极化": "",
      "SID": "",
      "color_channel": "#9933FF",
      "频道名称": "台海之声",
      "link_channel": "",
      "视频编码": "",
      "音频编码": "MPEG-1",
      "锁码方式": "开锁",
      "V-PID": "",
      "A-PID": "770",
      "发射基站": "株洲神农塔 茶陵云阳山",
      "高阶参数": "",
      "来源": "天涯海角 2022-10-17",
      "color_source": "#FF9933",
      "link_source": ""
    },
    {
      "频率": "530",
      "极化": "",
      "SID": "",
      "color_channel": "#9933FF",
      "频道名称": "神州之声",
      "link_channel": "",
      "视频编码": "",
      "音频编码": "MPEG-1",
      "锁码方式": "开锁",
      "V-PID": "",
      "A-PID": "780",
      "发射基站": "株洲神农塔 茶陵云阳山",
      "高阶参数": "",
      "来源": "天涯海角 2022-10-17",
      "color_source": "#FF9933",
      "link_source": ""
    },
    {
      "频率": "530",
      "极化": "",
      "SID": "",
      "color_channel": "#9933FF",
      "频道名称": "民族之声",
      "link_channel": "",
      "视频编码": "",
      "音频编码": "MPEG-1",
      "锁码方式": "开锁",
      "V-PID": "",
      "A-PID": "790",
      "发射基站": "株洲神农塔 茶陵云阳山",
      "高阶参数": "",
      "来源": "天涯海角 2022-10-17",
      "color_source": "#FF9933",
      "link_source": ""
    },
    {
      "频率": "530",
      "极化": "",
      "SID": "",
      "color_channel": "#9933FF",
      "频道名称": "文艺之声",
      "link_channel": "",
      "视频编码": "",
      "音频编码": "MPEG-1",
      "锁码方式": "开锁",
      "V-PID": "",
      "A-PID": "800",
      "发射基站": "株洲神农塔 茶陵云阳山",
      "高阶参数": "",
      "来源": "天涯海角 2022-10-17",
      "color_source": "#FF9933",
      "link_source": ""
    },
    {
      "频率": "530",
      "极化": "",
      "SID": "",
      "color_channel": "#9933FF",
      "频道名称": "老年之声",
      "link_channel": "",
      "视频编码": "",
      "音频编码": "MPEG-1",
      "锁码方式": "开锁",
      "V-PID": "",
      "A-PID": "810",
      "发射基站": "株洲神农塔 茶陵云阳山",
      "高阶参数": "",
      "来源": "天涯海角 2022-10-17",
      "color_source": "#FF9933",
      "link_source": ""
    },
    {
      "频率": "530",
      "极化": "",
      "SID": "",
      "color_channel": "#9933FF",
      "频道名称": "阅读之声",
      "link_channel": "",
      "视频编码": "",
      "音频编码": "MPEG-1",
      "锁码方式": "开锁",
      "V-PID": "",
      "A-PID": "820",
      "发射基站": "株洲神农塔 茶陵云阳山",
      "高阶参数": "",
      "来源": "天涯海角 2022-10-17",
      "color_source": "#FF9933",
      "link_source": ""
    },
    {
      "频率": "530",
      "极化": "",
      "SID": "",
      "color_channel": "#9933FF",
      "频道名称": "中国交通广播",
      "link_channel": "",
      "视频编码": "",
      "音频编码": "MPEG-1",
      "锁码方式": "开锁",
      "V-PID": "",
      "A-PID": "830",
      "发射基站": "株洲神农塔 茶陵云阳山",
      "高阶参数": "",
      "来源": "天涯海角 2022-10-17",
      "color_source": "#FF9933",
      "link_source": ""
    },
    {
      "频率": "530",
      "极化": "",
      "SID": "",
      "color_channel": "#9933FF",
      "频道名称": "中国乡村之声",
      "link_channel": "",
      "视频编码": "",
      "音频编码": "MPEG-1",
      "锁码方式": "开锁",
      "V-PID": "",
      "A-PID": "840",
      "发射基站": "株洲神农塔 茶陵云阳山",
      "高阶参数": "",
      "来源": "天涯海角 2022-10-17",
      "color_source": "#FF9933",
      "link_source": ""
    },
    {
      "频率": "554",
      "极化": "",
      "SID": "",
      "color_channel": "#666666",
      "频道名称": "河南卫视",
      "link_channel": "",
      "视频编码": "AVS+",
      "音频编码": "MPEG-1",
      "锁码方式": "",
      "V-PID": "",
      "A-PID": "",
      "发射基站": "株洲市声屏公司",
      "高阶参数": "",
      "来源": "413112784 2018-10-20",
      "color_source": "#666666",
      "link_source": ""
    },
    {
      "频率": "554",
      "极化": "",
      "SID": "",
      "color_channel": "#666666",
      "频道名称": "四川卫视",
      "link_channel": "",
      "视频编码": "AVS+",
      "音频编码": "MPEG-1",
      "锁码方式": "",
      "V-PID": "",
      "A-PID": "",
      "发射基站": "株洲市声屏公司",
      "高阶参数": "",
      "来源": "413112784 2018-10-20",
      "color_source": "#666666",
      "link_source": ""
    },
    {
      "频率": "554",
      "极化": "",
      "SID": "",
      "color_channel": "#666666",
      "频道名称": "中央电视台音乐频道",
      "link_channel": "",
      "视频编码": "AVS+",
      "音频编码": "MPEG-1",
      "锁码方式": "",
      "V-PID": "",
      "A-PID": "",
      "发射基站": "株洲市声屏公司",
      "高阶参数": "",
      "来源": "413112784 2018-10-20",
      "color_source": "#666666",
      "link_source": ""
    },
    {
      "频率": "554",
      "极化": "",
      "SID": "",
      "color_channel": "#666666",
      "频道名称": "湖南娱乐",
      "link_channel": "",
      "视频编码": "AVS+",
      "音频编码": "MPEG-1",
      "锁码方式": "",
      "V-PID": "",
      "A-PID": "",
      "发射基站": "株洲市声屏公司",
      "高阶参数": "",
      "来源": "413112784 2018-10-20",
      "color_source": "#666666",
      "link_source": ""
    },
    {
      "频率": "554",
      "极化": "",
      "SID": "",
      "color_channel": "#666666",
      "频道名称": "金鹰纪实",
      "link_channel": "",
      "视频编码": "AVS+",
      "音频编码": "MPEG-1",
      "锁码方式": "",
      "V-PID": "",
      "A-PID": "",
      "发射基站": "株洲市声屏公司",
      "高阶参数": "",
      "来源": "413112784 2018-10-20",
      "color_source": "#666666",
      "link_source": ""
    },
    {
      "频率": "554",
      "极化": "",
      "SID": "",
      "color_channel": "#666666",
      "频道名称": "中央电视台戏曲频道",
      "link_channel": "",
      "视频编码": "AVS+",
      "音频编码": "MPEG-1",
      "锁码方式": "",
      "V-PID": "",
      "A-PID": "",
      "发射基站": "株洲市声屏公司",
      "高阶参数": "",
      "来源": "413112784 2018-10-20",
      "color_source": "#666666",
      "link_source": ""
    },
    {
      "频率": "554",
      "极化": "",
      "SID": "",
      "color_channel": "#666666",
      "频道名称": "中华美食",
      "link_channel": "",
      "视频编码": "AVS+",
      "音频编码": "MPEG-1",
      "锁码方式": "",
      "V-PID": "",
      "A-PID": "",
      "发射基站": "株洲市声屏公司",
      "高阶参数": "",
      "来源": "413112784 2018-10-20",
      "color_source": "#666666",
      "link_source": ""
    },
    {
      "频率": "554",
      "极化": "",
      "SID": "",
      "color_channel": "#666666",
      "频道名称": "湖北卫视",
      "link_channel": "",
      "视频编码": "AVS+",
      "音频编码": "MPEG-1",
      "锁码方式": "",
      "V-PID": "",
      "A-PID": "",
      "发射基站": "株洲市声屏公司",
      "高阶参数": "",
      "来源": "413112784 2018-10-20",
      "color_source": "#666666",
      "link_source": ""
    },
    {
      "频率": "554",
      "极化": "",
      "SID": "",
      "color_channel": "#666666",
      "频道名称": "旅游卫视",
      "link_channel": "",
      "视频编码": "AVS+",
      "音频编码": "MPEG-1",
      "锁码方式": "",
      "V-PID": "",
      "A-PID": "",
      "发射基站": "株洲市声屏公司",
      "高阶参数": "",
      "来源": "413112784 2018-10-20",
      "color_source": "#666666",
      "link_source": ""
    },
    {
      "频率": "554",
      "极化": "",
      "SID": "",
      "color_channel": "#666666",
      "频道名称": "【预备频道】",
      "link_channel": "",
      "视频编码": "AVS+",
      "音频编码": "MPEG-1",
      "锁码方式": "",
      "V-PID": "",
      "A-PID": "",
      "发射基站": "株洲市声屏公司",
      "高阶参数": "",
      "来源": "413112784 2018-10-20",
      "color_source": "#666666",
      "link_source": ""
    },
    {
      "频率": "554",
      "极化": "",
      "SID": "",
      "color_channel": "#666666",
      "频道名称": "【预备频道】",
      "link_channel": "",
      "视频编码": "AVS+",
      "音频编码": "MPEG-1",
      "锁码方式": "",
      "V-PID": "",
      "A-PID": "",
      "发射基站": "株洲市声屏公司",
      "高阶参数": "",
      "来源": "413112784 2018-10-20",
      "color_source": "#666666",
      "link_source": ""
    },
    {
      "频率": "554",
      "极化": "",
      "SID": "",
      "color_channel": "#666666",
      "频道名称": "【预备频道】",
      "link_channel": "",
      "视频编码": "AVS+",
      "音频编码": "MPEG-1",
      "锁码方式": "",
      "V-PID": "",
      "A-PID": "",
      "发射基站": "株洲市声屏公司",
      "高阶参数": "",
      "来源": "413112784 2018-10-20",
      "color_source": "#666666",
      "link_source": ""
    },
    {
      "频率": "554",
      "极化": "",
      "SID": "",
      "color_channel": "#666666",
      "频道名称": "【预备频道】",
      "link_channel": "",
      "视频编码": "AVS+",
      "音频编码": "MPEG-1",
      "锁码方式": "",
      "V-PID": "",
      "A-PID": "",
      "发射基站": "株洲市声屏公司",
      "高阶参数": "",
      "来源": "413112784 2018-10-20",
      "color_source": "#666666",
      "link_source": ""
    },
    {
      "频率": "554",
      "极化": "",
      "SID": "",
      "color_channel": "#666666",
      "频道名称": "【预备频道】",
      "link_channel": "",
      "视频编码": "AVS+",
      "音频编码": "MPEG-1",
      "锁码方式": "",
      "V-PID": "",
      "A-PID": "",
      "发射基站": "株洲市声屏公司",
      "高阶参数": "",
      "来源": "413112784 2018-10-20",
      "color_source": "#666666",
      "link_source": ""
    },
    {
      "频率": "554",
      "极化": "",
      "SID": "",
      "color_channel": "#666666",
      "频道名称": "【预备频道】",
      "link_channel": "",
      "视频编码": "AVS+",
      "音频编码": "MPEG-1",
      "锁码方式": "",
      "V-PID": "",
      "A-PID": "",
      "发射基站": "株洲市声屏公司",
      "高阶参数": "",
      "来源": "413112784 2018-10-20",
      "color_source": "#666666",
      "link_source": ""
    },
    {
      "频率": "562",
      "极化": "",
      "SID": "",
      "color_channel": "#666666",
      "频道名称": "中央电视台综合频道",
      "link_channel": "",
      "视频编码": "MPEG-4",
      "音频编码": "MPEG-1",
      "锁码方式": "",
      "V-PID": "",
      "A-PID": "",
      "发射基站": "株洲市声屏公司 株洲神农塔",
      "高阶参数": "32QAM PN595 4/5（0.8）",
      "来源": "火星无线电2022-10-04",
      "color_source": "#FF9933",
      "link_source": ""
    },
    {
      "频率": "562",
      "极化": "",
      "SID": "",
      "color_channel": "#666666",
      "频道名称": "中央电视台音乐频道",
      "link_channel": "",
      "视频编码": "MPEG-4",
      "音频编码": "MPEG-1",
      "锁码方式": "",
      "V-PID": "",
      "A-PID": "",
      "发射基站": "株洲市声屏公司 株洲神农塔",
      "高阶参数": "32QAM PN595 4/5（0.8）",
      "来源": "火星无线电2022-10-04",
      "color_source": "#FF9933",
      "link_source": ""
    },
    {
      "频率": "562",
      "极化": "",
      "SID": "",
      "color_channel": "#666666",
      "频道名称": "湖南都市",
      "link_channel": "",
      "视频编码": "MPEG-4",
      "音频编码": "MPEG-1",
      "锁码方式": "",
      "V-PID": "",
      "A-PID": "",
      "发射基站": "株洲市声屏公司 株洲神农塔",
      "高阶参数": "32QAM PN595 4/5（0.8）",
      "来源": "火星无线电2022-10-04",
      "color_source": "#FF9933",
      "link_source": ""
    },
    {
      "频率": "562",
      "极化": "",
      "SID": "",
      "color_channel": "#666666",
      "频道名称": "中央电视台财经频道",
      "link_channel": "",
      "视频编码": "MPEG-4",
      "音频编码": "MPEG-1",
      "锁码方式": "",
      "V-PID": "",
      "A-PID": "",
      "发射基站": "株洲市声屏公司 株洲神农塔",
      "高阶参数": "32QAM PN595 4/5（0.8）",
      "来源": "火星无线电2022-10-04",
      "color_source": "#FF9933",
      "link_source": ""
    },
    {
      "频率": "562",
      "极化": "",
      "SID": "",
      "color_channel": "#666666",
      "频道名称": "地方戏曲",
      "link_channel": "",
      "视频编码": "MPEG-4",
      "音频编码": "MPEG-1",
      "锁码方式": "",
      "V-PID": "",
      "A-PID": "",
      "发射基站": "株洲市声屏公司 株洲神农塔",
      "高阶参数": "32QAM PN595 4/5（0.8）",
      "来源": "火星无线电2022-10-04",
      "color_source": "#FF9933",
      "link_source": ""
    },
    {
      "频率": "562",
      "极化": "",
      "SID": "",
      "color_channel": "#666666",
      "频道名称": "湖南卫视",
      "link_channel": "",
      "视频编码": "MPEG-4",
      "音频编码": "MPEG-1",
      "锁码方式": "",
      "V-PID": "",
      "A-PID": "",
      "发射基站": "株洲市声屏公司 株洲神农塔",
      "高阶参数": "32QAM PN595 4/5（0.8）",
      "来源": "火星无线电2022-10-04",
      "color_source": "#FF9933",
      "link_source": ""
    },
    {
      "频率": "562",
      "极化": "",
      "SID": "",
      "color_channel": "#666666",
      "频道名称": "中国气象",
      "link_channel": "",
      "视频编码": "MPEG-4",
      "音频编码": "MPEG-1",
      "锁码方式": "",
      "V-PID": "",
      "A-PID": "",
      "发射基站": "株洲市声屏公司 株洲神农塔",
      "高阶参数": "32QAM PN595 4/5（0.8）",
      "来源": "火星无线电2022-10-04",
      "color_source": "#FF9933",
      "link_source": ""
    },
    {
      "频率": "562",
      "极化": "",
      "SID": "",
      "color_channel": "#666666",
      "频道名称": "金鹰卡通",
      "link_channel": "",
      "视频编码": "MPEG-4",
      "音频编码": "MPEG-1",
      "锁码方式": "",
      "V-PID": "",
      "A-PID": "",
      "发射基站": "株洲市声屏公司 株洲神农塔",
      "高阶参数": "32QAM PN595 4/5（0.8）",
      "来源": "火星无线电2022-10-04",
      "color_source": "#FF9933",
      "link_source": ""
    },
    {
      "频率": "562",
      "极化": "",
      "SID": "",
      "color_channel": "#666666",
      "频道名称": "湖南娱乐",
      "link_channel": "",
      "视频编码": "MPEG-4",
      "音频编码": "MPEG-1",
      "锁码方式": "",
      "V-PID": "",
      "A-PID": "",
      "发射基站": "株洲市声屏公司 株洲神农塔",
      "高阶参数": "32QAM PN595 4/5（0.8）",
      "来源": "火星无线电2022-10-04",
      "color_source": "#FF9933",
      "link_source": ""
    },
    {
      "频率": "562",
      "极化": "",
      "SID": "",
      "color_channel": "#666666",
      "频道名称": "中央电视台综艺频道",
      "link_channel": "",
      "视频编码": "MPEG-4",
      "音频编码": "MPEG-1",
      "锁码方式": "",
      "V-PID": "",
      "A-PID": "",
      "发射基站": "株洲市声屏公司 株洲神农塔",
      "高阶参数": "32QAM PN595 4/5（0.8）",
      "来源": "火星无线电2022-10-04",
      "color_source": "#FF9933",
      "link_source": ""
    },
    {
      "频率": "562",
      "极化": "",
      "SID": "",
      "color_channel": "#666666",
      "频道名称": "中央电视台中文国际频道",
      "link_channel": "",
      "视频编码": "MPEG-4",
      "音频编码": "MPEG-1",
      "锁码方式": "",
      "V-PID": "",
      "A-PID": "",
      "发射基站": "株洲市声屏公司 株洲神农塔",
      "高阶参数": "32QAM PN595 4/5（0.8）",
      "来源": "火星无线电2022-10-04",
      "color_source": "#FF9933",
      "link_source": ""
    },
    {
      "频率": "562",
      "极化": "",
      "SID": "",
      "color_channel": "#666666",
      "频道名称": "湖南经视",
      "link_channel": "",
      "视频编码": "MPEG-4",
      "音频编码": "MPEG-1",
      "锁码方式": "",
      "V-PID": "",
      "A-PID": "",
      "发射基站": "株洲市声屏公司 株洲神农塔",
      "高阶参数": "32QAM PN595 4/5（0.8）",
      "来源": "火星无线电2022-10-04",
      "color_source": "#FF9933",
      "link_source": ""
    },
    {
      "频率": "562",
      "极化": "",
      "SID": "",
      "color_channel": "#666666",
      "频道名称": "中央电视台农业农村频道",
      "link_channel": "",
      "视频编码": "MPEG-4",
      "音频编码": "MPEG-1",
      "锁码方式": "",
      "V-PID": "",
      "A-PID": "",
      "发射基站": "株洲市声屏公司 株洲神农塔",
      "高阶参数": "32QAM PN595 4/5（0.8）",
      "来源": "火星无线电2022-10-04",
      "color_source": "#FF9933",
      "link_source": ""
    },
    {
      "频率": "562",
      "极化": "",
      "SID": "",
      "color_channel": "#808000",
      "频道名称": "无线导视",
      "link_channel": "",
      "视频编码": "MPEG-4",
      "音频编码": "MPEG-1",
      "锁码方式": "开锁",
      "V-PID": "",
      "A-PID": "",
      "发射基站": "株洲市声屏公司 株洲神农塔",
      "高阶参数": "32QAM PN595 4/5（0.8）",
      "来源": "火星无线电2022-10-04",
      "color_source": "#FF9933",
      "link_source": ""
    },
    {
      "频率": "562",
      "极化": "",
      "SID": "",
      "color_channel": "#808000",
      "频道名称": "株洲新闻综合",
      "link_channel": "",
      "视频编码": "MPEG-4",
      "音频编码": "MPEG-1",
      "锁码方式": "开锁",
      "V-PID": "",
      "A-PID": "",
      "发射基站": "株洲市声屏公司 株洲神农塔",
      "高阶参数": "32QAM PN595 4/5（0.8）",
      "来源": "火星无线电2022-10-04",
      "color_source": "#FF9933",
      "link_source": ""
    },
    {
      "频率": "618",
      "极化": "",
      "SID": "",
      "color_channel": "#666666",
      "频道名称": "时尚购物",
      "link_channel": "",
      "视频编码": "MPEG-4",
      "音频编码": "MPEG-1",
      "锁码方式": "",
      "V-PID": "",
      "A-PID": "",
      "发射基站": "渌口区",
      "高阶参数": "",
      "来源": "zhang wang129 2018-11-19",
      "color_source": "#666666",
      "link_source": ""
    },
    {
      "频率": "618",
      "极化": "",
      "SID": "",
      "color_channel": "#666666",
      "频道名称": "重庆卫视",
      "link_channel": "",
      "视频编码": "MPEG-4",
      "音频编码": "MPEG-1",
      "锁码方式": "",
      "V-PID": "",
      "A-PID": "",
      "发射基站": "渌口区",
      "高阶参数": "",
      "来源": "zhang wang129 2018-11-19",
      "color_source": "#666666",
      "link_source": ""
    },
    {
      "频率": "618",
      "极化": "",
      "SID": "",
      "color_channel": "#666666",
      "频道名称": "江西卫视",
      "link_channel": "",
      "视频编码": "MPEG-4",
      "音频编码": "MPEG-1",
      "锁码方式": "",
      "V-PID": "",
      "A-PID": "",
      "发射基站": "渌口区",
      "高阶参数": "",
      "来源": "zhang wang129 2018-11-19",
      "color_source": "#666666",
      "link_source": ""
    },
    {
      "频率": "618",
      "极化": "",
      "SID": "",
      "color_channel": "#666666",
      "频道名称": "安徽卫视",
      "link_channel": "",
      "视频编码": "MPEG-4",
      "音频编码": "MPEG-1",
      "锁码方式": "",
      "V-PID": "",
      "A-PID": "",
      "发射基站": "渌口区",
      "高阶参数": "",
      "来源": "zhang wang129 2018-11-19",
      "color_source": "#666666",
      "link_source": ""
    },
    {
      "频率": "618",
      "极化": "",
      "SID": "",
      "color_channel": "#666666",
      "频道名称": "北京卫视",
      "link_channel": "",
      "视频编码": "MPEG-4",
      "音频编码": "MPEG-1",
      "锁码方式": "",
      "V-PID": "",
      "A-PID": "",
      "发射基站": "渌口区",
      "高阶参数": "",
      "来源": "zhang wang129 2018-11-19",
      "color_source": "#666666",
      "link_source": ""
    },
    {
      "频率": "618",
      "极化": "",
      "SID": "",
      "color_channel": "#666666",
      "频道名称": "黑龙江卫视",
      "link_channel": "",
      "视频编码": "MPEG-4",
      "音频编码": "MPEG-1",
      "锁码方式": "",
      "V-PID": "",
      "A-PID": "",
      "发射基站": "渌口区",
      "高阶参数": "",
      "来源": "zhang wang129 2018-11-19",
      "color_source": "#666666",
      "link_source": ""
    },
    {
      "频率": "618",
      "极化": "",
      "SID": "",
      "color_channel": "#666666",
      "频道名称": "江苏卫视",
      "link_channel": "",
      "视频编码": "MPEG-4",
      "音频编码": "MPEG-1",
      "锁码方式": "",
      "V-PID": "",
      "A-PID": "",
      "发射基站": "渌口区",
      "高阶参数": "",
      "来源": "zhang wang129 2018-11-19",
      "color_source": "#666666",
      "link_source": ""
    },
    {
      "频率": "618",
      "极化": "",
      "SID": "",
      "color_channel": "#666666",
      "频道名称": "山东卫视",
      "link_channel": "",
      "视频编码": "MPEG-4",
      "音频编码": "MPEG-1",
      "锁码方式": "",
      "V-PID": "",
      "A-PID": "",
      "发射基站": "渌口区",
      "高阶参数": "",
      "来源": "zhang wang129 2018-11-19",
      "color_source": "#666666",
      "link_source": ""
    },
    {
      "频率": "618",
      "极化": "",
      "SID": "",
      "color_channel": "#666666",
      "频道名称": "地方戏曲",
      "link_channel": "",
      "视频编码": "MPEG-4",
      "音频编码": "MPEG-1",
      "锁码方式": "",
      "V-PID": "",
      "A-PID": "",
      "发射基站": "渌口区",
      "高阶参数": "",
      "来源": "zhang wang129 2018-11-19",
      "color_source": "#666666",
      "link_source": ""
    },
    {
      "频率": "618",
      "极化": "",
      "SID": "",
      "color_channel": "#666666",
      "频道名称": "株洲综合",
      "link_channel": "",
      "视频编码": "MPEG-4",
      "音频编码": "MPEG-1",
      "锁码方式": "",
      "V-PID": "",
      "A-PID": "",
      "发射基站": "渌口区",
      "高阶参数": "",
      "来源": "zhang wang129 2018-11-19",
      "color_source": "#666666",
      "link_source": ""
    },
    {
      "频率": "618",
      "极化": "",
      "SID": "80",
      "color_channel": "#339966",
      "频道名称": "湖南卫视高清频道",
      "link_channel": "",
      "视频编码": "AVS+",
      "音频编码": "MPEG-1",
      "锁码方式": "开锁",
      "V-PID": "81",
      "A-PID": "82",
      "发射基站": "株洲神农塔",
      "高阶参数": "16QAM PN420 4/5(0.8)",
      "来源": "火星无线电2022-10-04",
      "color_source": "#FF9933",
      "link_source": ""
    },
    {
      "频率": "618",
      "极化": "",
      "SID": "90",
      "color_channel": "#339966",
      "频道名称": "湖南经视高清频道",
      "link_channel": "",
      "视频编码": "AVS+",
      "音频编码": "MPEG-1",
      "锁码方式": "开锁",
      "V-PID": "91",
      "A-PID": "92",
      "发射基站": "株洲神农塔",
      "高阶参数": "16QAM PN420 4/5(0.8)",
      "来源": "火星无线电2022-10-04",
      "color_source": "#FF9933",
      "link_source": ""
    },
    {
      "频率": "618",
      "极化": "",
      "SID": "120",
      "color_channel": "#808000",
      "频道名称": "湖南都市",
      "link_channel": "",
      "视频编码": "AVS+",
      "音频编码": "MPEG-1",
      "锁码方式": "开锁",
      "V-PID": "121",
      "A-PID": "122",
      "发射基站": "株洲神农塔",
      "高阶参数": "16QAM PN420 4/5(0.8)",
      "来源": "火星无线电2022-10-04",
      "color_source": "#FF9933",
      "link_source": ""
    },
    {
      "频率": "618",
      "极化": "",
      "SID": "130",
      "color_channel": "#808000",
      "频道名称": "湖南电视剧",
      "link_channel": "",
      "视频编码": "AVS+",
      "音频编码": "MPEG-1",
      "锁码方式": "开锁",
      "V-PID": "131",
      "A-PID": "132",
      "发射基站": "株洲神农塔",
      "高阶参数": "16QAM PN420 4/5(0.8)",
      "来源": "火星无线电2022-10-04",
      "color_source": "#FF9933",
      "link_source": ""
    },
    {
      "频率": "618",
      "极化": "",
      "SID": "140",
      "color_channel": "#808000",
      "频道名称": "湖南娱乐",
      "link_channel": "",
      "视频编码": "AVS+",
      "音频编码": "MPEG-1",
      "锁码方式": "开锁",
      "V-PID": "141",
      "A-PID": "142",
      "发射基站": "株洲神农塔",
      "高阶参数": "16QAM PN420 4/5(0.8)",
      "来源": "火星无线电2022-10-04",
      "color_source": "#FF9933",
      "link_source": ""
    },
    {
      "频率": "618",
      "极化": "",
      "SID": "390",
      "color_channel": "#808000",
      "频道名称": "湖南教育",
      "link_channel": "",
      "视频编码": "AVS+",
      "音频编码": "MPEG-1",
      "锁码方式": "开锁",
      "V-PID": "391",
      "A-PID": "392",
      "发射基站": "株洲神农塔",
      "高阶参数": "16QAM PN420 4/5(0.8)",
      "来源": "火星无线电2022-10-04",
      "color_source": "#FF9933",
      "link_source": ""
    },
    {
      "频率": "618",
      "极化": "",
      "SID": "410",
      "color_channel": "#808000",
      "频道名称": "株洲新闻综合",
      "link_channel": "",
      "视频编码": "AVS+",
      "音频编码": "MPEG-1",
      "锁码方式": "开锁",
      "V-PID": "411",
      "A-PID": "412",
      "发射基站": "株洲神农塔",
      "高阶参数": "16QAM PN420 4/5(0.8)",
      "来源": "火星无线电2022-10-04",
      "color_source": "#FF9933",
      "link_source": ""
    },
    {
      "频率": "626",
      "极化": "",
      "SID": "80",
      "color_channel": "#339966",
      "频道名称": "湖南卫视高清频道",
      "link_channel": "",
      "视频编码": "AVS+",
      "音频编码": "MPEG-1",
      "锁码方式": "开锁",
      "V-PID": "81",
      "A-PID": "82",
      "发射基站": "株洲神农塔",
      "高阶参数": "64QAM 3/5(0.6)",
      "来源": "南方开星 2022-08-11",
      "color_source": "#FF9933",
      "link_source": ""
    },
    {
      "频率": "626",
      "极化": "",
      "SID": "90",
      "color_channel": "#339966",
      "频道名称": "湖南经视高清频道",
      "link_channel": "",
      "视频编码": "AVS+",
      "音频编码": "MPEG-1",
      "锁码方式": "开锁",
      "V-PID": "91",
      "A-PID": "92",
      "发射基站": "株洲神农塔",
      "高阶参数": "64QAM 3/5(0.6)",
      "来源": "南方开星 2022-08-11",
      "color_source": "#FF9933",
      "link_source": ""
    },
    {
      "频率": "626",
      "极化": "",
      "SID": "120",
      "color_channel": "#808000",
      "频道名称": "湖南都市",
      "link_channel": "",
      "视频编码": "AVS+",
      "音频编码": "MPEG-1",
      "锁码方式": "开锁",
      "V-PID": "121",
      "A-PID": "122",
      "发射基站": "株洲神农塔",
      "高阶参数": "64QAM 3/5(0.6)",
      "来源": "南方开星 2022-08-11",
      "color_source": "#FF9933",
      "link_source": ""
    },
    {
      "频率": "626",
      "极化": "",
      "SID": "130",
      "color_channel": "#808000",
      "频道名称": "湖南电视剧",
      "link_channel": "",
      "视频编码": "AVS+",
      "音频编码": "MPEG-1",
      "锁码方式": "开锁",
      "V-PID": "131",
      "A-PID": "132",
      "发射基站": "株洲神农塔",
      "高阶参数": "64QAM 3/5(0.6)",
      "来源": "南方开星 2022-08-11",
      "color_source": "#FF9933",
      "link_source": ""
    },
    {
      "频率": "626",
      "极化": "",
      "SID": "140",
      "color_channel": "#808000",
      "频道名称": "湖南娱乐",
      "link_channel": "",
      "视频编码": "AVS+",
      "音频编码": "MPEG-1",
      "锁码方式": "开锁",
      "V-PID": "141",
      "A-PID": "142",
      "发射基站": "株洲神农塔",
      "高阶参数": "64QAM 3/5(0.6)",
      "来源": "南方开星 2022-08-11",
      "color_source": "#FF9933",
      "link_source": ""
    },
    {
      "频率": "626",
      "极化": "",
      "SID": "250",
      "color_channel": "#808000",
      "频道名称": "中央电视台纪录频道",
      "link_channel": "",
      "视频编码": "AVS+",
      "音频编码": "MPEG-1",
      "锁码方式": "开锁",
      "V-PID": "251",
      "A-PID": "252",
      "发射基站": "株洲神农塔",
      "高阶参数": "64QAM 3/5(0.6)",
      "来源": "南方开星 2022-08-11",
      "color_source": "#FF9933",
      "link_source": ""
    },
    {
      "频率": "626",
      "极化": "",
      "SID": "330",
      "color_channel": "#808000",
      "频道名称": "中央电视台国防军事频道",
      "link_channel": "",
      "视频编码": "AVS+",
      "音频编码": "MPEG-1",
      "锁码方式": "开锁",
      "V-PID": "331",
      "A-PID": "332",
      "发射基站": "株洲神农塔",
      "高阶参数": "64QAM 3/5(0.6)",
      "来源": "南方开星 2022-08-11",
      "color_source": "#FF9933",
      "link_source": ""
    },
    {
      "频率": "626",
      "极化": "",
      "SID": "350",
      "color_channel": "#808000",
      "频道名称": "中央电视台戏曲频道",
      "link_channel": "",
      "视频编码": "AVS+",
      "音频编码": "MPEG-1",
      "锁码方式": "开锁",
      "V-PID": "351",
      "A-PID": "352",
      "发射基站": "株洲神农塔",
      "高阶参数": "64QAM 3/5(0.6)",
      "来源": "南方开星 2022-08-11",
      "color_source": "#FF9933",
      "link_source": ""
    },
    {
      "频率": "626",
      "极化": "",
      "SID": "370",
      "color_channel": "#808000",
      "频道名称": "中央电视台新闻频道",
      "link_channel": "",
      "视频编码": "AVS+",
      "音频编码": "MPEG-1",
      "锁码方式": "开锁",
      "V-PID": "371",
      "A-PID": "372",
      "发射基站": "株洲神农塔",
      "高阶参数": "64QAM 3/5(0.6)",
      "来源": "南方开星 2022-08-11",
      "color_source": "#FF9933",
      "link_source": ""
    },
    {
      "频率": "626",
      "极化": "",
      "SID": "390",
      "color_channel": "#808000",
      "频道名称": "湖南教育",
      "link_channel": "",
      "视频编码": "AVS+",
      "音频编码": "MPEG-1",
      "锁码方式": "开锁",
      "V-PID": "391",
      "A-PID": "392",
      "发射基站": "株洲神农塔",
      "高阶参数": "64QAM 3/5(0.6)",
      "来源": "南方开星 2022-08-11",
      "color_source": "#FF9933",
      "link_source": ""
    },
    {
      "频率": "626",
      "极化": "",
      "SID": "410",
      "color_channel": "#808000",
      "频道名称": "株洲新闻综合",
      "link_channel": "",
      "视频编码": "AVS+",
      "音频编码": "MPEG-1",
      "锁码方式": "开锁",
      "V-PID": "411",
      "A-PID": "412",
      "发射基站": "株洲神农塔",
      "高阶参数": "64QAM 3/5(0.6)",
      "来源": "南方开星 2022-08-11",
      "color_source": "#FF9933",
      "link_source": ""
    },
    {
      "频率": "626",
      "极化": "",
      "SID": "401",
      "color_channel": "#808000",
      "频道名称": "中央电视台农业农村频道",
      "link_channel": "",
      "视频编码": "AVS+",
      "音频编码": "DRA",
      "锁码方式": "NDS",
      "V-PID": "512",
      "A-PID": "650",
      "发射基站": "茶陵云阳山",
      "高阶参数": "64QAM 3/4(0.6)",
      "来源": "q1060896983 2024-02-08",
      "color_source": "#FF9933",
      "link_source": ""
    },
    {
      "频率": "626",
      "极化": "",
      "SID": "402",
      "color_channel": "#808000",
      "频道名称": "中央电视台纪录频道",
      "link_channel": "",
      "视频编码": "AVS+",
      "音频编码": "DRA",
      "锁码方式": "NDS",
      "V-PID": "513",
      "A-PID": "660",
      "发射基站": "茶陵云阳山",
      "高阶参数": "64QAM 3/4(0.6)",
      "来源": "q1060896983 2024-02-08",
      "color_source": "#FF9933",
      "link_source": ""
    },
    {
      "频率": "626",
      "极化": "",
      "SID": "403",
      "color_channel": "#808000",
      "频道名称": "中央电视台戏曲频道",
      "link_channel": "",
      "视频编码": "AVS+",
      "音频编码": "DRA",
      "锁码方式": "NDS",
      "V-PID": "514",
      "A-PID": "670",
      "发射基站": "茶陵云阳山",
      "高阶参数": "64QAM 3/4(0.6)",
      "来源": "q1060896983 2024-02-08",
      "color_source": "#FF9933",
      "link_source": ""
    },
    {
      "频率": "626",
      "极化": "",
      "SID": "404",
      "color_channel": "#808000",
      "频道名称": "中央电视台新闻频道",
      "link_channel": "",
      "视频编码": "AVS+",
      "音频编码": "DRA",
      "锁码方式": "NDS",
      "V-PID": "515",
      "A-PID": "680",
      "发射基站": "茶陵云阳山",
      "高阶参数": "64QAM 3/4(0.6)",
      "来源": "q1060896983 2024-02-08",
      "color_source": "#FF9933",
      "link_source": ""
    },
    {
      "频率": "642",
      "极化": "",
      "SID": "",
      "color_channel": "#666666",
      "频道名称": "时尚购物",
      "link_channel": "",
      "视频编码": "MPEG-4",
      "音频编码": "MPEG-1",
      "锁码方式": "",
      "V-PID": "",
      "A-PID": "",
      "发射基站": "渌口区",
      "高阶参数": "",
      "来源": "华容小禹 2018-09-23",
      "color_source": "#666666",
      "link_source": ""
    },
    {
      "频率": "642",
      "极化": "",
      "SID": "",
      "color_channel": "#666666",
      "频道名称": "重庆卫视",
      "link_channel": "",
      "视频编码": "MPEG-4",
      "音频编码": "MPEG-1",
      "锁码方式": "",
      "V-PID": "",
      "A-PID": "",
      "发射基站": "渌口区",
      "高阶参数": "",
      "来源": "华容小禹 2018-09-23",
      "color_source": "#666666",
      "link_source": ""
    },
    {
      "频率": "642",
      "极化": "",
      "SID": "",
      "color_channel": "#666666",
      "频道名称": "江西卫视",
      "link_channel": "",
      "视频编码": "MPEG-4",
      "音频编码": "MPEG-1",
      "锁码方式": "",
      "V-PID": "",
      "A-PID": "",
      "发射基站": "渌口区",
      "高阶参数": "",
      "来源": "华容小禹 2018-09-23",
      "color_source": "#666666",
      "link_source": ""
    },
    {
      "频率": "642",
      "极化": "",
      "SID": "",
      "color_channel": "#666666",
      "频道名称": "安徽卫视",
      "link_channel": "",
      "视频编码": "MPEG-4",
      "音频编码": "MPEG-1",
      "锁码方式": "",
      "V-PID": "",
      "A-PID": "",
      "发射基站": "渌口区",
      "高阶参数": "",
      "来源": "华容小禹 2018-09-23",
      "color_source": "#666666",
      "link_source": ""
    },
    {
      "频率": "642",
      "极化": "",
      "SID": "",
      "color_channel": "#666666",
      "频道名称": "北京卫视",
      "link_channel": "",
      "视频编码": "MPEG-4",
      "音频编码": "MPEG-1",
      "锁码方式": "",
      "V-PID": "",
      "A-PID": "",
      "发射基站": "渌口区",
      "高阶参数": "",
      "来源": "华容小禹 2018-09-23",
      "color_source": "#666666",
      "link_source": ""
    },
    {
      "频率": "642",
      "极化": "",
      "SID": "",
      "color_channel": "#666666",
      "频道名称": "黑龙江卫视",
      "link_channel": "",
      "视频编码": "MPEG-4",
      "音频编码": "MPEG-1",
      "锁码方式": "",
      "V-PID": "",
      "A-PID": "",
      "发射基站": "渌口区",
      "高阶参数": "",
      "来源": "华容小禹 2018-09-23",
      "color_source": "#666666",
      "link_source": ""
    },
    {
      "频率": "642",
      "极化": "",
      "SID": "",
      "color_channel": "#666666",
      "频道名称": "江苏卫视",
      "link_channel": "",
      "视频编码": "MPEG-4",
      "音频编码": "MPEG-1",
      "锁码方式": "",
      "V-PID": "",
      "A-PID": "",
      "发射基站": "渌口区",
      "高阶参数": "",
      "来源": "华容小禹 2018-09-23",
      "color_source": "#666666",
      "link_source": ""
    },
    {
      "频率": "642",
      "极化": "",
      "SID": "",
      "color_channel": "#666666",
      "频道名称": "山东卫视",
      "link_channel": "",
      "视频编码": "MPEG-4",
      "音频编码": "MPEG-1",
      "锁码方式": "",
      "V-PID": "",
      "A-PID": "",
      "发射基站": "渌口区",
      "高阶参数": "",
      "来源": "华容小禹 2018-09-23",
      "color_source": "#666666",
      "link_source": ""
    },
    {
      "频率": "642",
      "极化": "",
      "SID": "",
      "color_channel": "#666666",
      "频道名称": "地方戏曲",
      "link_channel": "",
      "视频编码": "MPEG-4",
      "音频编码": "MPEG-1",
      "锁码方式": "",
      "V-PID": "",
      "A-PID": "",
      "发射基站": "渌口区",
      "高阶参数": "",
      "来源": "华容小禹 2018-09-23",
      "color_source": "#666666",
      "link_source": ""
    },
    {
      "频率": "642",
      "极化": "",
      "SID": "",
      "color_channel": "#666666",
      "频道名称": "株洲综合",
      "link_channel": "",
      "视频编码": "MPEG-4",
      "音频编码": "MPEG-1",
      "锁码方式": "",
      "V-PID": "",
      "A-PID": "",
      "发射基站": "渌口区",
      "高阶参数": "",
      "来源": "华容小禹 2018-09-23",
      "color_source": "#666666",
      "link_source": ""
    },
    {
      "频率": "650",
      "极化": "",
      "SID": "",
      "color_channel": "#666666",
      "频道名称": "中央电视台综合频道",
      "link_channel": "",
      "视频编码": "MPEG-4",
      "音频编码": "MPEG-1",
      "锁码方式": "",
      "V-PID": "",
      "A-PID": "",
      "发射基站": "渌口区",
      "高阶参数": "",
      "来源": "zhang wang129 2018-11-24",
      "color_source": "#666666",
      "link_source": ""
    },
    {
      "频率": "650",
      "极化": "",
      "SID": "",
      "color_channel": "#666666",
      "频道名称": "中央电视台经济频道",
      "link_channel": "",
      "视频编码": "MPEG-4",
      "音频编码": "MPEG-1",
      "锁码方式": "",
      "V-PID": "",
      "A-PID": "",
      "发射基站": "渌口区",
      "高阶参数": "",
      "来源": "zhang wang129 2018-11-24",
      "color_source": "#666666",
      "link_source": ""
    },
    {
      "频率": "650",
      "极化": "",
      "SID": "",
      "color_channel": "#666666",
      "频道名称": "中央电视台中文国际频道",
      "link_channel": "",
      "视频编码": "MPEG-4",
      "音频编码": "MPEG-1",
      "锁码方式": "",
      "V-PID": "",
      "A-PID": "",
      "发射基站": "渌口区",
      "高阶参数": "",
      "来源": "zhang wang129 2018-11-24",
      "color_source": "#666666",
      "link_source": ""
    },
    {
      "频率": "650",
      "极化": "",
      "SID": "",
      "color_channel": "#666666",
      "频道名称": "中央电视台农业农村频道",
      "link_channel": "",
      "视频编码": "MPEG-4",
      "音频编码": "MPEG-1",
      "锁码方式": "",
      "V-PID": "",
      "A-PID": "",
      "发射基站": "渌口区",
      "高阶参数": "",
      "来源": "zhang wang129 2018-11-24",
      "color_source": "#666666",
      "link_source": ""
    },
    {
      "频率": "650",
      "极化": "",
      "SID": "",
      "color_channel": "#666666",
      "频道名称": "中央电视台科教频道",
      "link_channel": "http://www.cctv.com",
      "视频编码": "MPEG-4",
      "音频编码": "MPEG-1",
      "锁码方式": "",
      "V-PID": "",
      "A-PID": "",
      "发射基站": "渌口区",
      "高阶参数": "",
      "来源": "zhang wang129 2018-11-24",
      "color_source": "#666666",
      "link_source": ""
    },
    {
      "频率": "650",
      "极化": "",
      "SID": "",
      "color_channel": "#666666",
      "频道名称": "中央电视台戏曲频道",
      "link_channel": "http://www.cctv.com",
      "视频编码": "MPEG-4",
      "音频编码": "MPEG-1",
      "锁码方式": "",
      "V-PID": "",
      "A-PID": "",
      "发射基站": "渌口区",
      "高阶参数": "",
      "来源": "zhang wang129 2018-11-24",
      "color_source": "#666666",
      "link_source": ""
    },
    {
      "频率": "650",
      "极化": "",
      "SID": "",
      "color_channel": "#666666",
      "频道名称": "中央电视台社会与法频道",
      "link_channel": "http://www.cctv.com",
      "视频编码": "MPEG-4",
      "音频编码": "MPEG-1",
      "锁码方式": "",
      "V-PID": "",
      "A-PID": "",
      "发射基站": "渌口区",
      "高阶参数": "",
      "来源": "zhang wang129 2018-11-24",
      "color_source": "#666666",
      "link_source": ""
    },
    {
      "频率": "650",
      "极化": "",
      "SID": "",
      "color_channel": "#666666",
      "频道名称": "中央电视台新闻频道",
      "link_channel": "http://www.cctv.com",
      "视频编码": "MPEG-4",
      "音频编码": "MPEG-1",
      "锁码方式": "",
      "V-PID": "",
      "A-PID": "",
      "发射基站": "渌口区",
      "高阶参数": "",
      "来源": "zhang wang129 2018-11-24",
      "color_source": "#666666",
      "link_source": ""
    },
    {
      "频率": "650",
      "极化": "",
      "SID": "",
      "color_channel": "#666666",
      "频道名称": "中央电视台少儿频道",
      "link_channel": "",
      "视频编码": "MPEG-4",
      "音频编码": "MPEG-1",
      "锁码方式": "",
      "V-PID": "",
      "A-PID": "",
      "发射基站": "渌口区",
      "高阶参数": "",
      "来源": "zhang wang129 2018-11-24",
      "color_source": "#666666",
      "link_source": ""
    },
    {
      "频率": "650",
      "极化": "",
      "SID": "",
      "color_channel": "#666666",
      "频道名称": "中央电视台音乐频道",
      "link_channel": "http://www.cctv.com",
      "视频编码": "MPEG-4",
      "音频编码": "MPEG-1",
      "锁码方式": "",
      "V-PID": "",
      "A-PID": "",
      "发射基站": "渌口区",
      "高阶参数": "",
      "来源": "zhang wang129 2018-11-24",
      "color_source": "#666666",
      "link_source": ""
    },
    {
      "频率": "666",
      "极化": "",
      "SID": "401",
      "color_channel": "#808000",
      "频道名称": "中央电视台农业农村频道",
      "link_channel": "",
      "视频编码": "AVS+",
      "音频编码": "DRA",
      "锁码方式": "NDS",
      "V-PID": "512",
      "A-PID": "650",
      "发射基站": "麟游县",
      "高阶参数": "",
      "来源": "只关注中文卫星 2022-10-03",
      "color_source": "#FF9933",
      "link_source": ""
    },
    {
      "频率": "666",
      "极化": "",
      "SID": "402",
      "color_channel": "#808000",
      "频道名称": "中央电视台纪录频道",
      "link_channel": "",
      "视频编码": "AVS+",
      "音频编码": "DRA",
      "锁码方式": "NDS",
      "V-PID": "513",
      "A-PID": "660",
      "发射基站": "麟游县",
      "高阶参数": "",
      "来源": "只关注中文卫星 2022-10-03",
      "color_source": "#FF9933",
      "link_source": ""
    },
    {
      "频率": "666",
      "极化": "",
      "SID": "403",
      "color_channel": "#808000",
      "频道名称": "中央电视台戏曲频道",
      "link_channel": "",
      "视频编码": "AVS+",
      "音频编码": "DRA",
      "锁码方式": "NDS",
      "V-PID": "514",
      "A-PID": "670",
      "发射基站": "麟游县",
      "高阶参数": "",
      "来源": "只关注中文卫星 2022-10-03",
      "color_source": "#FF9933",
      "link_source": ""
    },
    {
      "频率": "666",
      "极化": "",
      "SID": "404",
      "color_channel": "#808000",
      "频道名称": "中国环球电视网新闻频道",
      "link_channel": "",
      "视频编码": "AVS+",
      "音频编码": "DRA",
      "锁码方式": "NDS",
      "V-PID": "515",
      "A-PID": "680",
      "发射基站": "麟游县",
      "高阶参数": "",
      "来源": "只关注中文卫星 2022-10-03",
      "color_source": "#FF9933",
      "link_source": ""
    },
    {
      "频率": "666",
      "极化": "",
      "SID": "",
      "color_channel": "#666666",
      "频道名称": "湖南经视",
      "link_channel": "",
      "视频编码": "MPEG-4",
      "音频编码": "MPEG-1",
      "锁码方式": "",
      "V-PID": "",
      "A-PID": "",
      "发射基站": "渌口区",
      "高阶参数": "",
      "来源": "华容小禹 2018-09-23",
      "color_source": "#666666",
      "link_source": ""
    },
    {
      "频率": "666",
      "极化": "",
      "SID": "",
      "color_channel": "#666666",
      "频道名称": "湖南都市",
      "link_channel": "",
      "视频编码": "MPEG-4",
      "音频编码": "MPEG-1",
      "锁码方式": "",
      "V-PID": "",
      "A-PID": "",
      "发射基站": "渌口区",
      "高阶参数": "",
      "来源": "华容小禹 2018-09-23",
      "color_source": "#666666",
      "link_source": ""
    },
    {
      "频率": "666",
      "极化": "",
      "SID": "",
      "color_channel": "#808000",
      "频道名称": "渌湘新闻综合",
      "link_channel": "",
      "视频编码": "MPEG-4",
      "音频编码": "MPEG-1",
      "锁码方式": "开锁",
      "V-PID": "",
      "A-PID": "",
      "发射基站": "渌口区",
      "高阶参数": "",
      "来源": "华容小禹 2018-09-23",
      "color_source": "#666666",
      "link_source": ""
    },
    {
      "频率": "666",
      "极化": "",
      "SID": "",
      "color_channel": "#666666",
      "频道名称": "中央电视台综艺频道",
      "link_channel": "",
      "视频编码": "MPEG-4",
      "音频编码": "MPEG-1",
      "锁码方式": "",
      "V-PID": "",
      "A-PID": "",
      "发射基站": "渌口区",
      "高阶参数": "",
      "来源": "华容小禹 2018-09-23",
      "color_source": "#666666",
      "link_source": ""
    },
    {
      "频率": "666",
      "极化": "",
      "SID": "",
      "color_channel": "#666666",
      "频道名称": "湖南娱乐",
      "link_channel": "",
      "视频编码": "MPEG-4",
      "音频编码": "MPEG-1",
      "锁码方式": "",
      "V-PID": "",
      "A-PID": "",
      "发射基站": "渌口区",
      "高阶参数": "",
      "来源": "华容小禹 2018-09-23",
      "color_source": "#666666",
      "link_source": ""
    },
    {
      "频率": "666",
      "极化": "",
      "SID": "",
      "color_channel": "#666666",
      "频道名称": "中央电视台电视剧频道",
      "link_channel": "",
      "视频编码": "MPEG-4",
      "音频编码": "MPEG-1",
      "锁码方式": "",
      "V-PID": "",
      "A-PID": "",
      "发射基站": "渌口区",
      "高阶参数": "",
      "来源": "华容小禹 2018-09-23",
      "color_source": "#666666",
      "link_source": ""
    },
    {
      "频率": "666",
      "极化": "",
      "SID": "",
      "color_channel": "#666666",
      "频道名称": "湖南电视剧",
      "link_channel": "",
      "视频编码": "MPEG-4",
      "音频编码": "MPEG-1",
      "锁码方式": "",
      "V-PID": "",
      "A-PID": "",
      "发射基站": "渌口区",
      "高阶参数": "",
      "来源": "华容小禹 2018-09-23",
      "color_source": "#666666",
      "link_source": ""
    },
    {
      "频率": "666",
      "极化": "",
      "SID": "",
      "color_channel": "#666666",
      "频道名称": "福建东南卫视",
      "link_channel": "",
      "视频编码": "MPEG-4",
      "音频编码": "MPEG-1",
      "锁码方式": "",
      "V-PID": "",
      "A-PID": "",
      "发射基站": "渌口区",
      "高阶参数": "",
      "来源": "华容小禹 2018-09-23",
      "color_source": "#666666",
      "link_source": ""
    },
    {
      "频率": "666",
      "极化": "",
      "SID": "",
      "color_channel": "#666666",
      "频道名称": "湖南卫视",
      "link_channel": "",
      "视频编码": "MPEG-4",
      "音频编码": "MPEG-1",
      "锁码方式": "",
      "V-PID": "",
      "A-PID": "",
      "发射基站": "渌口区",
      "高阶参数": "",
      "来源": "华容小禹 2018-09-23",
      "color_source": "#666666",
      "link_source": ""
    },
    {
      "频率": "682",
      "极化": "水平",
      "SID": "",
      "color_channel": "#666666",
      "频道名称": "广西卫视",
      "link_channel": "",
      "视频编码": "MPEG-4",
      "音频编码": "MPEG-1",
      "锁码方式": "",
      "V-PID": "",
      "A-PID": "",
      "发射基站": "渌口区",
      "高阶参数": "",
      "来源": "华容小禹 2018-09-23",
      "color_source": "#666666",
      "link_source": ""
    },
    {
      "频率": "682",
      "极化": "水平",
      "SID": "",
      "color_channel": "#666666",
      "频道名称": "黄金院线",
      "link_channel": "",
      "视频编码": "MPEG-4",
      "音频编码": "MPEG-1",
      "锁码方式": "",
      "V-PID": "",
      "A-PID": "",
      "发射基站": "渌口区",
      "高阶参数": "",
      "来源": "华容小禹 2018-09-23",
      "color_source": "#666666",
      "link_source": ""
    },
    {
      "频率": "682",
      "极化": "水平",
      "SID": "",
      "color_channel": "#666666",
      "频道名称": "乒团卫视",
      "link_channel": "",
      "视频编码": "MPEG-4",
      "音频编码": "MPEG-1",
      "锁码方式": "",
      "V-PID": "",
      "A-PID": "",
      "发射基站": "渌口区",
      "高阶参数": "",
      "来源": "华容小禹 2018-09-23",
      "color_source": "#666666",
      "link_source": ""
    },
    {
      "频率": "682",
      "极化": "水平",
      "SID": "",
      "color_channel": "#666666",
      "频道名称": "湖北卫视",
      "link_channel": "",
      "视频编码": "MPEG-4",
      "音频编码": "MPEG-1",
      "锁码方式": "",
      "V-PID": "",
      "A-PID": "",
      "发射基站": "渌口区",
      "高阶参数": "",
      "来源": "华容小禹 2018-09-23",
      "color_source": "#666666",
      "link_source": ""
    },
    {
      "频率": "682",
      "极化": "水平",
      "SID": "",
      "color_channel": "#666666",
      "频道名称": "国防军事",
      "link_channel": "",
      "视频编码": "MPEG-4",
      "音频编码": "MPEG-1",
      "锁码方式": "",
      "V-PID": "",
      "A-PID": "",
      "发射基站": "渌口区",
      "高阶参数": "",
      "来源": "华容小禹 2018-09-23",
      "color_source": "#666666",
      "link_source": ""
    },
    {
      "频率": "682",
      "极化": "水平",
      "SID": "",
      "color_channel": "#666666",
      "频道名称": "炫动卡通",
      "link_channel": "",
      "视频编码": "MPEG-4",
      "音频编码": "MPEG-1",
      "锁码方式": "",
      "V-PID": "",
      "A-PID": "",
      "发射基站": "渌口区",
      "高阶参数": "",
      "来源": "华容小禹 2018-09-23",
      "color_source": "#666666",
      "link_source": ""
    },
    {
      "频率": "682",
      "极化": "水平",
      "SID": "",
      "color_channel": "#666666",
      "频道名称": "宁夏卫视",
      "link_channel": "",
      "视频编码": "MPEG-4",
      "音频编码": "MPEG-1",
      "锁码方式": "",
      "V-PID": "",
      "A-PID": "",
      "发射基站": "渌口区",
      "高阶参数": "",
      "来源": "华容小禹 2018-09-23",
      "color_source": "#666666",
      "link_source": ""
    },
    {
      "频率": "682",
      "极化": "水平",
      "SID": "",
      "color_channel": "#666666",
      "频道名称": "陕西农林卫视",
      "link_channel": "",
      "视频编码": "MPEG-4",
      "音频编码": "MPEG-1",
      "锁码方式": "",
      "V-PID": "",
      "A-PID": "",
      "发射基站": "渌口区",
      "高阶参数": "",
      "来源": "华容小禹 2018-09-23",
      "color_source": "#666666",
      "link_source": ""
    },
    {
      "频率": "682",
      "极化": "水平",
      "SID": "",
      "color_channel": "#808000",
      "频道名称": "河南卫视",
      "link_channel": "",
      "视频编码": "MPEG-4",
      "音频编码": "MPEG-1",
      "锁码方式": "",
      "V-PID": "",
      "A-PID": "",
      "发射基站": "渌口区",
      "高阶参数": "",
      "来源": "华容小禹 2018-09-23",
      "color_source": "#666666",
      "link_source": ""
    },
    {
      "频率": "690",
      "极化": "",
      "SID": "",
      "color_channel": "#808000",
      "频道名称": "央视指南",
      "link_channel": "",
      "视频编码": "MPEG-4",
      "音频编码": "MPEG-1",
      "锁码方式": "开锁",
      "V-PID": "",
      "A-PID": "",
      "发射基站": "渌口区",
      "高阶参数": "",
      "来源": "华容小禹 2018-09-23",
      "color_source": "#666666",
      "link_source": ""
    },
    {
      "频率": "690",
      "极化": "",
      "SID": "",
      "color_channel": "#666666",
      "频道名称": "【预备频道】",
      "link_channel": "",
      "视频编码": "MPEG-4",
      "音频编码": "MPEG-1",
      "锁码方式": "",
      "V-PID": "",
      "A-PID": "",
      "发射基站": "渌口区",
      "高阶参数": "",
      "来源": "华容小禹 2018-09-23",
      "color_source": "#666666",
      "link_source": ""
    },
    {
      "频率": "690",
      "极化": "",
      "SID": "",
      "color_channel": "#666666",
      "频道名称": "【预备频道】",
      "link_channel": "",
      "视频编码": "MPEG-4",
      "音频编码": "MPEG-1",
      "锁码方式": "",
      "V-PID": "",
      "A-PID": "",
      "发射基站": "渌口区",
      "高阶参数": "",
      "来源": "华容小禹 2018-09-23",
      "color_source": "#666666",
      "link_source": ""
    },
    {
      "频率": "690",
      "极化": "",
      "SID": "",
      "color_channel": "#666666",
      "频道名称": "【预备频道】",
      "link_channel": "",
      "视频编码": "MPEG-4",
      "音频编码": "MPEG-1",
      "锁码方式": "",
      "V-PID": "",
      "A-PID": "",
      "发射基站": "渌口区",
      "高阶参数": "",
      "来源": "华容小禹 2018-09-23",
      "color_source": "#666666",
      "link_source": ""
    },
    {
      "频率": "690",
      "极化": "",
      "SID": "",
      "color_channel": "#666666",
      "频道名称": "【预备频道】",
      "link_channel": "",
      "视频编码": "MPEG-4",
      "音频编码": "MPEG-1",
      "锁码方式": "",
      "V-PID": "",
      "A-PID": "",
      "发射基站": "渌口区",
      "高阶参数": "",
      "来源": "华容小禹 2018-09-23",
      "color_source": "#666666",
      "link_source": ""
    },
    {
      "频率": "690",
      "极化": "",
      "SID": "",
      "color_channel": "#666666",
      "频道名称": "【预备频道】",
      "link_channel": "",
      "视频编码": "MPEG-4",
      "音频编码": "MPEG-1",
      "锁码方式": "",
      "V-PID": "",
      "A-PID": "",
      "发射基站": "渌口区",
      "高阶参数": "",
      "来源": "华容小禹 2018-09-23",
      "color_source": "#666666",
      "link_source": ""
    },
    {
      "频率": "690",
      "极化": "",
      "SID": "",
      "color_channel": "#666666",
      "频道名称": "【预备频道】",
      "link_channel": "",
      "视频编码": "MPEG-4",
      "音频编码": "MPEG-1",
      "锁码方式": "",
      "V-PID": "",
      "A-PID": "",
      "发射基站": "渌口区",
      "高阶参数": "",
      "来源": "华容小禹 2018-09-23",
      "color_source": "#666666",
      "link_source": ""
    },
    {
      "频率": "690",
      "极化": "",
      "SID": "",
      "color_channel": "#666666",
      "频道名称": "【预备频道】",
      "link_channel": "",
      "视频编码": "MPEG-4",
      "音频编码": "MPEG-1",
      "锁码方式": "",
      "V-PID": "",
      "A-PID": "",
      "发射基站": "渌口区",
      "高阶参数": "",
      "来源": "华容小禹 2018-09-23",
      "color_source": "#666666",
      "link_source": ""
    },
    {
      "频率": "690",
      "极化": "",
      "SID": "",
      "color_channel": "#666666",
      "频道名称": "【预备频道】",
      "link_channel": "",
      "视频编码": "MPEG-4",
      "音频编码": "MPEG-1",
      "锁码方式": "",
      "V-PID": "",
      "A-PID": "",
      "发射基站": "渌口区",
      "高阶参数": "",
      "来源": "华容小禹 2018-09-23",
      "color_source": "#666666",
      "link_source": ""
    },
    {
      "频率": "690",
      "极化": "",
      "SID": "",
      "color_channel": "#666666",
      "频道名称": "【预备频道】",
      "link_channel": "",
      "视频编码": "MPEG-4",
      "音频编码": "MPEG-1",
      "锁码方式": "",
      "V-PID": "",
      "A-PID": "",
      "发射基站": "渌口区",
      "高阶参数": "",
      "来源": "华容小禹 2018-09-23",
      "color_source": "#666666",
      "link_source": ""
    },
    {
      "频率": "690",
      "极化": "",
      "SID": "",
      "color_channel": "#666666",
      "频道名称": "导视",
      "link_channel": "",
      "视频编码": "AVS+",
      "音频编码": "MPEG-1",
      "锁码方式": "",
      "V-PID": "",
      "A-PID": "",
      "发射基站": "株洲市声屏公司",
      "高阶参数": "",
      "来源": "413112784 2018-10-20",
      "color_source": "#666666",
      "link_source": ""
    },
    {
      "频率": "690",
      "极化": "",
      "SID": "",
      "color_channel": "#666666",
      "频道名称": "株洲综合",
      "link_channel": "",
      "视频编码": "AVS+",
      "音频编码": "MPEG-1",
      "锁码方式": "",
      "V-PID": "",
      "A-PID": "",
      "发射基站": "株洲市声屏公司",
      "高阶参数": "",
      "来源": "413112784 2018-10-20",
      "color_source": "#666666",
      "link_source": ""
    },
    {
      "频率": "690",
      "极化": "",
      "SID": "",
      "color_channel": "#666666",
      "频道名称": "株洲法制",
      "link_channel": "",
      "视频编码": "AVS+",
      "音频编码": "MPEG-1",
      "锁码方式": "",
      "V-PID": "",
      "A-PID": "",
      "发射基站": "株洲市声屏公司",
      "高阶参数": "",
      "来源": "413112784 2018-10-20",
      "color_source": "#666666",
      "link_source": ""
    },
    {
      "频率": "690",
      "极化": "",
      "SID": "",
      "color_channel": "#666666",
      "频道名称": "长沙政法",
      "link_channel": "",
      "视频编码": "AVS+",
      "音频编码": "MPEG-1",
      "锁码方式": "",
      "V-PID": "",
      "A-PID": "",
      "发射基站": "株洲市声屏公司",
      "高阶参数": "",
      "来源": "413112784 2018-10-20",
      "color_source": "#666666",
      "link_source": ""
    },
    {
      "频率": "690",
      "极化": "",
      "SID": "",
      "color_channel": "#666666",
      "频道名称": "金鹰卡通",
      "link_channel": "",
      "视频编码": "AVS+",
      "音频编码": "MPEG-1",
      "锁码方式": "",
      "V-PID": "",
      "A-PID": "",
      "发射基站": "株洲市声屏公司",
      "高阶参数": "",
      "来源": "413112784 2018-10-20",
      "color_source": "#666666",
      "link_source": ""
    },
    {
      "频率": "690",
      "极化": "",
      "SID": "",
      "color_channel": "#666666",
      "频道名称": "湖南爱晚",
      "link_channel": "",
      "视频编码": "AVS+",
      "音频编码": "MPEG-1",
      "锁码方式": "",
      "V-PID": "",
      "A-PID": "",
      "发射基站": "株洲市声屏公司",
      "高阶参数": "",
      "来源": "413112784 2018-10-20",
      "color_source": "#666666",
      "link_source": ""
    },
    {
      "频率": "690",
      "极化": "",
      "SID": "",
      "color_channel": "#666666",
      "频道名称": "家有购物",
      "link_channel": "",
      "视频编码": "AVS+",
      "音频编码": "MPEG-1",
      "锁码方式": "",
      "V-PID": "",
      "A-PID": "",
      "发射基站": "株洲市声屏公司",
      "高阶参数": "",
      "来源": "413112784 2018-10-20",
      "color_source": "#666666",
      "link_source": ""
    },
    {
      "频率": "690",
      "极化": "",
      "SID": "",
      "color_channel": "#666666",
      "频道名称": "国防军事",
      "link_channel": "",
      "视频编码": "AVS+",
      "音频编码": "MPEG-1",
      "锁码方式": "",
      "V-PID": "",
      "A-PID": "",
      "发射基站": "株洲市声屏公司",
      "高阶参数": "",
      "来源": "413112784 2018-10-20",
      "color_source": "#666666",
      "link_source": ""
    },
    {
      "频率": "690",
      "极化": "",
      "SID": "",
      "color_channel": "#666666",
      "频道名称": "湖南卫视",
      "link_channel": "",
      "视频编码": "AVS+",
      "音频编码": "MPEG-1",
      "锁码方式": "",
      "V-PID": "",
      "A-PID": "",
      "发射基站": "株洲市声屏公司",
      "高阶参数": "",
      "来源": "413112784 2018-10-20",
      "color_source": "#666666",
      "link_source": ""
    },
    {
      "频率": "690",
      "极化": "",
      "SID": "",
      "color_channel": "#666666",
      "频道名称": "湖南经视",
      "link_channel": "",
      "视频编码": "AVS+",
      "音频编码": "MPEG-1",
      "锁码方式": "",
      "V-PID": "",
      "A-PID": "",
      "发射基站": "株洲市声屏公司",
      "高阶参数": "",
      "来源": "413112784 2018-10-20",
      "color_source": "#666666",
      "link_source": ""
    },
    {
      "频率": "690",
      "极化": "",
      "SID": "",
      "color_channel": "#666666",
      "频道名称": "湖南都市",
      "link_channel": "",
      "视频编码": "AVS+",
      "音频编码": "MPEG-1",
      "锁码方式": "",
      "V-PID": "",
      "A-PID": "",
      "发射基站": "株洲市声屏公司",
      "高阶参数": "",
      "来源": "413112784 2018-10-20",
      "color_source": "#666666",
      "link_source": ""
    },
    {
      "频率": "690",
      "极化": "",
      "SID": "",
      "color_channel": "#666666",
      "频道名称": "湖南电视剧",
      "link_channel": "",
      "视频编码": "AVS+",
      "音频编码": "MPEG-1",
      "锁码方式": "",
      "V-PID": "",
      "A-PID": "",
      "发射基站": "株洲市声屏公司",
      "高阶参数": "",
      "来源": "413112784 2018-10-20",
      "color_source": "#666666",
      "link_source": ""
    },
    {
      "频率": "690",
      "极化": "",
      "SID": "",
      "color_channel": "#666666",
      "频道名称": "山东卫视",
      "link_channel": "",
      "视频编码": "AVS+",
      "音频编码": "MPEG-1",
      "锁码方式": "",
      "V-PID": "",
      "A-PID": "",
      "发射基站": "株洲市声屏公司",
      "高阶参数": "",
      "来源": "413112784 2018-10-20",
      "color_source": "#666666",
      "link_source": ""
    },
    {
      "频率": "690",
      "极化": "",
      "SID": "",
      "color_channel": "#666666",
      "频道名称": "浙江卫视",
      "link_channel": "",
      "视频编码": "AVS+",
      "音频编码": "MPEG-1",
      "锁码方式": "",
      "V-PID": "",
      "A-PID": "",
      "发射基站": "株洲市声屏公司",
      "高阶参数": "",
      "来源": "413112784 2018-10-20",
      "color_source": "#666666",
      "link_source": ""
    },
    {
      "频率": "690",
      "极化": "",
      "SID": "",
      "color_channel": "#666666",
      "频道名称": "地方戏曲",
      "link_channel": "",
      "视频编码": "AVS+",
      "音频编码": "MPEG-1",
      "锁码方式": "",
      "V-PID": "",
      "A-PID": "",
      "发射基站": "株洲市声屏公司",
      "高阶参数": "",
      "来源": "413112784 2018-10-20",
      "color_source": "#666666",
      "link_source": ""
    },
    {
      "频率": "698",
      "极化": "水平",
      "SID": "",
      "color_channel": "#666666",
      "频道名称": "四川卫视",
      "link_channel": "",
      "视频编码": "MPEG-4",
      "音频编码": "MPEG-1",
      "锁码方式": "",
      "V-PID": "",
      "A-PID": "",
      "发射基站": "渌口区",
      "高阶参数": "",
      "来源": "华容小禹 2018-09-23",
      "color_source": "#666666",
      "link_source": ""
    },
    {
      "频率": "698",
      "极化": "水平",
      "SID": "",
      "color_channel": "#666666",
      "频道名称": "深圳卫视",
      "link_channel": "",
      "视频编码": "MPEG-4",
      "音频编码": "MPEG-1",
      "锁码方式": "",
      "V-PID": "",
      "A-PID": "",
      "发射基站": "渌口区",
      "高阶参数": "",
      "来源": "华容小禹 2018-09-23",
      "color_source": "#666666",
      "link_source": ""
    },
    {
      "频率": "698",
      "极化": "水平",
      "SID": "",
      "color_channel": "#666666",
      "频道名称": "贵州卫视",
      "link_channel": "",
      "视频编码": "MPEG-4",
      "音频编码": "MPEG-1",
      "锁码方式": "",
      "V-PID": "",
      "A-PID": "",
      "发射基站": "渌口区",
      "高阶参数": "",
      "来源": "华容小禹 2018-09-23",
      "color_source": "#666666",
      "link_source": ""
    },
    {
      "频率": "698",
      "极化": "水平",
      "SID": "",
      "color_channel": "#666666",
      "频道名称": "中国教育电视一套",
      "link_channel": "",
      "视频编码": "MPEG-4",
      "音频编码": "MPEG-1",
      "锁码方式": "",
      "V-PID": "",
      "A-PID": "",
      "发射基站": "渌口区",
      "高阶参数": "",
      "来源": "华容小禹 2018-09-23",
      "color_source": "#666666",
      "link_source": ""
    },
    {
      "频率": "698",
      "极化": "水平",
      "SID": "",
      "color_channel": "#666666",
      "频道名称": "上海东方卫视",
      "link_channel": "",
      "视频编码": "MPEG-4",
      "音频编码": "MPEG-1",
      "锁码方式": "",
      "V-PID": "",
      "A-PID": "",
      "发射基站": "渌口区",
      "高阶参数": "",
      "来源": "华容小禹 2018-09-23",
      "color_source": "#666666",
      "link_source": ""
    },
    {
      "频率": "698",
      "极化": "水平",
      "SID": "",
      "color_channel": "#666666",
      "频道名称": "天津卫视",
      "link_channel": "",
      "视频编码": "MPEG-4",
      "音频编码": "MPEG-1",
      "锁码方式": "",
      "V-PID": "",
      "A-PID": "",
      "发射基站": "渌口区",
      "高阶参数": "",
      "来源": "华容小禹 2018-09-23",
      "color_source": "#666666",
      "link_source": ""
    },
    {
      "频率": "698",
      "极化": "水平",
      "SID": "",
      "color_channel": "#666666",
      "频道名称": "浙江卫视",
      "link_channel": "",
      "视频编码": "MPEG-4",
      "音频编码": "MPEG-1",
      "锁码方式": "",
      "V-PID": "",
      "A-PID": "",
      "发射基站": "渌口区",
      "高阶参数": "",
      "来源": "华容小禹 2018-09-23",
      "color_source": "#666666",
      "link_source": ""
    },
    {
      "频率": "698",
      "极化": "水平",
      "SID": "",
      "color_channel": "#666666",
      "频道名称": "广东卫视",
      "link_channel": "",
      "视频编码": "MPEG-4",
      "音频编码": "MPEG-1",
      "锁码方式": "",
      "V-PID": "",
      "A-PID": "",
      "发射基站": "渌口区",
      "高阶参数": "",
      "来源": "华容小禹 2018-09-23",
      "color_source": "#666666",
      "link_source": ""
    },
    {
      "频率": "698",
      "极化": "水平",
      "SID": "",
      "color_channel": "#666666",
      "频道名称": "云南旅游",
      "link_channel": "",
      "视频编码": "MPEG-4",
      "音频编码": "MPEG-1",
      "锁码方式": "",
      "V-PID": "",
      "A-PID": "",
      "发射基站": "渌口区",
      "高阶参数": "",
      "来源": "华容小禹 2018-09-23",
      "color_source": "#666666",
      "link_source": ""
    },
    {
      "频率": "698",
      "极化": "水平",
      "SID": "",
      "color_channel": "#666666",
      "频道名称": "云南卫视",
      "link_channel": "",
      "视频编码": "MPEG-4",
      "音频编码": "MPEG-1",
      "锁码方式": "",
      "V-PID": "",
      "A-PID": "",
      "发射基站": "渌口区",
      "高阶参数": "",
      "来源": "华容小禹 2018-09-23",
      "color_source": "#666666",
      "link_source": ""
    }
  ]
}